aiq/meta/pypi.md
aiq/plugins/redis/__init__.py
aiq/plugins/redis/memory.py
aiq/plugins/redis/redis_editor.py
aiq/plugins/redis/register.py
aiq/plugins/redis/schema.py
aiqtoolkit_redis-1.2.0a20250806.dist-info/METADATA
aiqtoolkit_redis-1.2.0a20250806.dist-info/WHEEL
aiqtoolkit_redis-1.2.0a20250806.dist-info/entry_points.txt
aiqtoolkit_redis-1.2.0a20250806.dist-info/top_level.txt
aiqtoolkit_redis-1.2.0a20250806.dist-info/RECORD
