Metadata-Version: 2.4
Name: aiqtoolkit-redis
Version: 1.2.0a20250806
Summary: Subpackage for Redis memory integration in AIQtoolkit
Keywords: ai,agents,memory
Classifier: Programming Language :: Python
Requires-Python: <3.13,>=3.11
Requires-Dist: aiqtoolkit==v1.2.0a20250806
Requires-Dist: redis~=4.3.4
